twitterSentiment/__init__.py
twitterSentiment/twitterSentiment.py
twitter_sentiment-0.0.6.1.dist-info/LICENSE
twitter_sentiment-0.0.6.1.dist-info/METADATA
twitter_sentiment-0.0.6.1.dist-info/WHEEL
twitter_sentiment-0.0.6.1.dist-info/top_level.txt
twitter_sentiment-0.0.6.1.dist-info/RECORD
