Metadata-Version: 2.1
Name: twitter-sentiment
Version: 0.0.6.1
Summary: Twitter sentiment is a Python library leveraging NLP and the Twitter API to determine the emotion of a tweet
Home-page: https://github.com/TeddyCr/twitter-sentiment
Author: Teddy Crepineau
Author-email: teddy.crepineau@gmail.com
License: UNKNOWN
Platform: UNKNOWN
Classifier: Programming Language :: Python :: 3.6
Classifier: License :: OSI Approved :: MIT License
Classifier: Operating System :: MacOS
Classifier: Development Status :: 4 - Beta
Classifier: Programming Language :: Python :: 3.6
Classifier: Intended Audience :: Other Audience
Classifier: Topic :: Scientific/Engineering :: Artificial Intelligence
